Metadata-Version: 2.1
Name: gfm2html
Version: 2020.7.2
Summary: github flavored markdown to html
Home-page: https://github.com/andrewp-as-is/gfm2html.py
License: Unlicense
Keywords: github flavored markdown
Platform: UNKNOWN
Classifier: License :: Public Domain
Classifier: Operating System :: OS Independent
Classifier: Programming Language :: Python :: 3
